README.rst
setup.py
stutils/__init__.py
stutils.egg-info/PKG-INFO
stutils.egg-info/SOURCES.txt
stutils.egg-info/dependency_links.txt
stutils.egg-info/entry_points.txt
stutils.egg-info/requires.txt
stutils.egg-info/top_level.txt
stutils/pandas/__init__.py
stutils/pandas/pdfastapply.py