Metadata-Version: 1.1
Name: stutils
Version: 0.0.9
Summary: Utils for fast work with Pandas
Home-page: https://github.com/anuzhny/stutils
Author: Anton Nuzhny
Author-email: anton.nuzhny@gmail.com
License: GPL
Keywords: sample setuptools development
Platform: UNKNOWN
Classifier: Development Status :: 2 - Pre-Alpha
Classifier: Intended Audience :: Science/Research
Classifier: License :: OSI Approved :: GNU General Public License (GPL)
Classifier: Programming Language :: Python :: 2
